README.md
setup.py
coatl/Browser.py
coatl/Functions.py
coatl/Graph.py
coatl/Logger.py
coatl/Main.py
coatl/Tree.py
coatl/__init__.py
coatl.egg-info/PKG-INFO
coatl.egg-info/SOURCES.txt
coatl.egg-info/dependency_links.txt
coatl.egg-info/requires.txt
coatl.egg-info/top_level.txt