Metadata-Version: 1.1
Name: coatl
Version: 0.0
Summary: For data analysis
Home-page: https://github.com/threemeninaboat3247/coatl
Author: Yuki Arai
Author-email: threemeninaboat3247@gmail.com
License: MIT
Keywords: data analysis
Platform: UNKNOWN
Classifier: Programming Language :: Python
Classifier: Intended Audience :: Science/Research
Classifier: License :: OSI Approved :: MIT License
